Orf_sendMsg/__init__.py
Orf_sendMsg/wxSend.py
Orf_sendMsg/logo/bug.png
Orf_sendMsg/logo/dgr.png
Orf_sendMsg/logo/msg.png
Orf_sendMsg/logo/orf.png
Orf_sendMsg/logo/war.png
Orf_sendMsg-0.0.5.dist-info/METADATA
Orf_sendMsg-0.0.5.dist-info/WHEEL
Orf_sendMsg-0.0.5.dist-info/top_level.txt
Orf_sendMsg-0.0.5.dist-info/RECORD
