Metadata-Version: 2.1
Name: Orf-sendMsg
Version: 0.0.5
Summary: For persional use.
Home-page: UNKNOWN
Author: Brief
Author-email: brf2053@gmail.com
License: UNKNOWN
Platform: UNKNOWN
Classifier: License :: OSI Approved :: MIT License
Classifier: Programming Language :: Python :: 3
Requires-Python: >=3.5
Requires-Dist: requests
